arkdata/__init__.py
arkdata/blueprints/__init__.py
arkdata/blueprints/ammunition.py
arkdata/blueprints/armour.py
arkdata/blueprints/artifact.py
arkdata/blueprints/attachment.py
arkdata/blueprints/consumable.py
arkdata/blueprints/creature.py
arkdata/blueprints/dye.py
arkdata/blueprints/egg.py
arkdata/blueprints/farm.py
arkdata/blueprints/recipe.py
arkdata/blueprints/resource.py
arkdata/blueprints/saddle.py
arkdata/blueprints/seed.py
arkdata/blueprints/skin.py
arkdata/blueprints/structure.py
arkdata/blueprints/tool.py
arkdata/blueprints/trophy.py
arkdata/blueprints/weapon.py
arkdata/database/__init__.py
arkdata/database/configuration.py
arkdata/database/cursor.py
arkdata/database/table.py
arkdata/models/__init__.py
arkdata/models/account.py
arkdata/models/cart_item.py
arkdata/models/command.py
arkdata/models/order_item.py
arkdata/models/product.py
arkdata/models/sessions.py
arkdata/models/user.py
arkdata/nitrado/__init__.py
arkdata/nitrado/gameserver.py
arkdata/nitrado/log.py
arkdata/nitrado/player.py
arkdata/nitrado/service.py
arkdata-1.0.72.dist-info/LICENSE
arkdata-1.0.72.dist-info/METADATA
arkdata-1.0.72.dist-info/WHEEL
arkdata-1.0.72.dist-info/top_level.txt
arkdata-1.0.72.dist-info/RECORD
