Metadata-Version: 2.1
Name: arkdata
Version: 1.0.72
Summary: This application accesses the Ark system.
Home-page: https://github.com/GameServerGurus/Ark-Data
Author: Mauricio
Author-email: dev.mauricio.lomeli@gmail.com
Project-URL: Bug Tracker, https://github.com/GameServerGurus/Ark-Data/issues
Platform: win32
Classifier: Programming Language :: Python :: 3.9
Classifier: Programming Language :: Python :: 3.10
Classifier: Programming Language :: Python :: 3.11
Classifier: License :: OSI Approved :: MIT License
Classifier: Operating System :: OS Independent
Requires-Python: >=3.9
License-File: LICENSE
Requires-Dist: requests (>=2.28.1)
Requires-Dist: python-dotenv (>=1.0.0)
Requires-Dist: SQLAlchemy (>=2.0.9)
Requires-Dist: sqlalchemy-utils (>=0.40.0)
Requires-Dist: flask (>=2.2.3)
Provides-Extra: testing
Requires-Dist: pytest (>=6.0) ; extra == 'testing'
Requires-Dist: pytest-cov (>=2.0) ; extra == 'testing'
Requires-Dist: mypy (>=0.971) ; extra == 'testing'
Requires-Dist: flake8 (>=3.9) ; extra == 'testing'
Requires-Dist: tox (>=3.24) ; extra == 'testing'
